mpms.py
mpms-2.6.0.2.dist-info/METADATA
mpms-2.6.0.2.dist-info/WHEEL
mpms-2.6.0.2.dist-info/top_level.txt
mpms-2.6.0.2.dist-info/RECORD
