Metadata-Version: 2.4
Name: mpms
Version: 2.6.0.2
Summary: Simple python Multiprocesses-Multithreads task queue
Home-page: https://github.com/aploium/mpms
Author: aploium
Author-email: i@z.codes
Project-URL: Source, https://github.com/aploium/mpms
Project-URL: Changelog, https://github.com/aploium/mpms/blob/master/CHANGELOG.md
Platform: any
Classifier: Development Status :: 4 - Beta
Classifier: Operating System :: OS Independent
Classifier: Programming Language :: Python
Classifier: Programming Language :: Python :: 3
Classifier: Programming Language :: Python :: 3 :: Only
Classifier: Programming Language :: Python :: 3.10
Classifier: Programming Language :: Python :: 3.11
Classifier: Programming Language :: Python :: 3.12
Classifier: Programming Language :: Python :: 3.13
Requires-Python: >=3.10
Requires-Dist: cloudpickle>=3.0.0
Dynamic: author
Dynamic: author-email
Dynamic: classifier
Dynamic: description
Dynamic: description-content-type
Dynamic: home-page
Dynamic: platform
Dynamic: project-url
Dynamic: requires-dist
Dynamic: requires-python
Dynamic: summary
